github_archive/__init__.py
github_archive/_version.py
github_archive/archive.py
github_archive/cli.py
github_archive/constants.py
github_archive/gists.py
github_archive/logger.py
github_archive/py.typed
github_archive/repos.py
github_archive-7.0.0.dist-info/licenses/LICENSE
github_archive-7.0.0.dist-info/METADATA
github_archive-7.0.0.dist-info/WHEEL
github_archive-7.0.0.dist-info/entry_points.txt
github_archive-7.0.0.dist-info/top_level.txt
github_archive-7.0.0.dist-info/RECORD
