Metadata-Version: 2.4
Name: github-archive
Version: 7.0.0
Summary: A powerful tool to concurrently clone, pull, or fork user and org repos and gists to create a GitHub archive.
Home-page: http://github.com/justintime50/github-archive
Author: Justintime50
License: MIT
Classifier: Programming Language :: Python :: 3
Classifier: License :: OSI Approved :: MIT License
Classifier: Operating System :: OS Independent
Requires-Python: >=3.10, <4
License-File: LICENSE
Requires-Dist: PyGithub==2.8.*
Requires-Dist: woodchips==2.*
Provides-Extra: dev
Requires-Dist: bandit==1.9.*; extra == "dev"
Requires-Dist: black==25.*; extra == "dev"
Requires-Dist: build==1.3.*; extra == "dev"
Requires-Dist: flake8==7.*; extra == "dev"
Requires-Dist: isort==7.*; extra == "dev"
Requires-Dist: mypy==1.18.*; extra == "dev"
Requires-Dist: pytest==9.*; extra == "dev"
Requires-Dist: pytest-cov==7.*; extra == "dev"
Dynamic: author
Dynamic: classifier
Dynamic: description
Dynamic: description-content-type
Dynamic: home-page
Dynamic: license
Dynamic: license-file
Dynamic: provides-extra
Dynamic: requires-dist
Dynamic: requires-python
Dynamic: summary
